{ "stocks": [ 
{ "nse_code":"TITAN","nse_name":"Titan Company Limited","last_p":862.95,"v52_hi":872,"v52_lo":307.1,"v6_rate":914.73,"v10_rate":949.25,"v12_rate":966.5,"v_time6":0,"v_time10":0,"v_time12":0,"close":862.95,"last_pr":130.41,"rise_count":10,"drop_count":2,"avg_m_rise":7.65,"v_m1":"Ja","v_low1":356.9,"v_high1":378.45,"v_m2":"Fb","v_low2":359,"v_high2":458.5,"v_m3":"Ma","v_low3":428,"v_high3":470.6,"v_m4":"Ap","v_low4":455.8,"v_high4":495.55,"v_m5":"My","v_low5":460.1,"v_high5":506.15,"v_m6":"Jn","v_low6":465.3,"v_high6":569,"v_m7":"Ju","v_low7":520,"v_high7":546.95,"v_m8":"Ag","v_low8":538.1,"v_high8":638.3,"v_m9":"Sp","v_low9":563.65,"v_high9":654.2,"v_m10":"Oc","v_low10":582.1,"v_high10":639.5,"v_m11":"Nv","v_low11":634.5,"v_high11":838.9,"v_m12":"Dc","v_low12":770,"v_high12":872,"a_buy":0,"a_sell":0,"b_buy":0,"b_sell":0,"c_buy":0,"c_sell":0 }
,{ "nse_code":"SUNTV","nse_name":"Sun TV Network Limited","last_p":936.5,"v52_hi":964,"v52_lo":469.35,"v6_rate":992.69,"v10_rate":1030.15,"v12_rate":1048.88,"v_time6":0,"v_time10":0,"v_time12":0,"close":936.5,"last_pr":77.06,"rise_count":8,"drop_count":4,"avg_m_rise":5.55,"v_m1":"Ja","v_low1":515.05,"v_high1":544.45,"v_m2":"Fb","v_low2":525.85,"v_high2":774,"v_m3":"Ma","v_low3":702,"v_high3":797.85,"v_m4":"Ap","v_low4":768.5,"v_high4":946,"v_m5":"My","v_low5":768.5,"v_high5":936,"v_m6":"Jn","v_low6":778.8,"v_high6":865,"v_m7":"Ju","v_low7":773.65,"v_high7":845,"v_m8":"Ag","v_low8":652.45,"v_high8":807.45,"v_m9":"Sp","v_low9":710,"v_high9":865.5,"v_m10":"Oc","v_low10":756,"v_high10":872.8,"v_m11":"Nv","v_low11":826.65,"v_high11":915.8,"v_m12":"Dc","v_low12":826.65,"v_high12":964,"a_buy":0,"a_sell":0,"b_buy":0,"b_sell":0,"c_buy":0,"c_sell":0 }
,{ "nse_code":"DLF","nse_name":"DLF Limited","last_p":245.25,"v52_hi":249,"v52_lo":101,"v6_rate":259.97,"v10_rate":269.78,"v12_rate":274.68,"v_time6":0,"v_time10":0,"v_time12":0,"close":245.25,"last_pr":77.86,"rise_count":10,"drop_count":2,"avg_m_rise":5.26,"v_m1":"Ja","v_low1":125.1,"v_high1":140,"v_m2":"Fb","v_low2":134.3,"v_high2":152.4,"v_m3":"Ma","v_low3":139.15,"v_high3":155.4,"v_m4":"Ap","v_low4":146.2,"v_high4":197.45,"v_m5":"My","v_low5":170.2,"v_high5":216,"v_m6":"Jn","v_low6":171.4,"v_high6":204,"v_m7":"Ju","v_low7":189.75,"v_high7":207.2,"v_m8":"Ag","v_low8":153,"v_high8":196.3,"v_m9":"Sp","v_low9":158.2,"v_high9":198.6,"v_m10":"Oc","v_low10":166,"v_high10":202.7,"v_m11":"Nv","v_low11":194.15,"v_high11":234.9,"v_m12":"Dc","v_low12":220.95,"v_high12":249,"a_buy":0,"a_sell":0,"b_buy":0,"b_sell":0,"c_buy":0,"c_sell":0 }
,{ "nse_code":"BAJFINANCE","nse_name":"Bajaj Finance Limited","last_p":1770.4,"v52_hi":1985.9,"v52_lo":760.5,"v6_rate":1876.62,"v10_rate":1947.44,"v12_rate":1982.85,"v_time6":2,"v_time10":2,"v_time12":1,"close":1770.4,"last_pr":66.51,"rise_count":9,"drop_count":3,"avg_m_rise":4.57,"v_m1":"Ja","v_low1":894.45,"v_high1":1072,"v_m2":"Fb","v_low2":1025,"v_high2":1119,"v_m3":"Ma","v_low3":1019.1,"v_high3":1206,"v_m4":"Ap","v_low4":1162,"v_high4":1349.9,"v_m5":"My","v_low5":1190.55,"v_high5":1374,"v_m6":"Jn","v_low6":1313.9,"v_high6":1433,"v_m7":"Ju","v_low7":1366.5,"v_high7":1739.8,"v_m8":"Ag","v_low8":1590,"v_high8":1837.4,"v_m9":"Sp","v_low9":1759,"v_high9":1985.9,"v_m10":"Oc","v_low10":1700.1,"v_high10":1973.7,"v_m11":"Nv","v_low11":1707.05,"v_high11":1848,"v_m12":"Dc","v_low12":1627.05,"v_high12":1785,"a_buy":0,"a_sell":0,"b_buy":0,"b_sell":0,"c_buy":0,"c_sell":0 }
,{ "nse_code":"MARUTI","nse_name":"Maruti Suzuki India Limited","last_p":9733.9,"v52_hi":9996.4,"v52_lo":5041,"v6_rate":10317.93,"v10_rate":10707.29,"v12_rate":10901.97,"v_time6":0,"v_time10":0,"v_time12":0,"close":9733.9,"last_pr":68.32,"rise_count":11,"drop_count":1,"avg_m_rise":4.52,"v_m1":"Ja","v_low1":5642,"v_high1":5939,"v_m2":"Fb","v_low2":5842.2,"v_high2":6233.9,"v_m3":"Ma","v_low3":5800,"v_high3":6226.8,"v_m4":"Ap","v_low4":6021,"v_high4":6589.8,"v_m5":"My","v_low5":6602,"v_high5":7248,"v_m6":"Jn","v_low6":7085.05,"v_high6":7481,"v_m7":"Ju","v_low7":6700,"v_high7":7765,"v_m8":"Ag","v_low8":7380,"v_high8":7920,"v_m9":"Sp","v_low9":7651,"v_high9":8200,"v_m10":"Oc","v_low10":7690,"v_high10":8279,"v_m11":"Nv","v_low11":8080,"v_high11":8696,"v_m12":"Dc","v_low12":8450.05,"v_high12":9996.4,"a_buy":0,"a_sell":0,"b_buy":0,"b_sell":0,"c_buy":0,"c_sell":0 }
,{ "nse_code":"BAJAJFINSV","nse_name":"Bajaj Finserv Limited","last_p":5312.7,"v52_hi":5790,"v52_lo":2541.3,"v6_rate":5631.46,"v10_rate":5843.97,"v12_rate":5950.22,"v_time6":1,"v_time10":0,"v_time12":0,"close":5312.7,"last_pr":59.98,"rise_count":7,"drop_count":5,"avg_m_rise":4.33,"v_m1":"Ja","v_low1":2993.5,"v_high1":3338,"v_m2":"Fb","v_low2":3166,"v_high2":3980,"v_m3":"Ma","v_low3":3740,"v_high3":4217,"v_m4":"Ap","v_low4":4065,"v_high4":4750,"v_m5":"My","v_low5":3801,"v_high5":4671.75,"v_m6":"Jn","v_low6":3950,"v_high6":4343,"v_m7":"Ju","v_low7":4080,"v_high7":5098,"v_m8":"Ag","v_low8":4913,"v_high8":5630,"v_m9":"Sp","v_low9":5001.75,"v_high9":5790,"v_m10":"Oc","v_low10":4827.1,"v_high10":5448.8,"v_m11":"Nv","v_low11":4850,"v_high11":5349,"v_m12":"Dc","v_low12":4905,"v_high12":5340,"a_buy":0,"a_sell":0,"b_buy":0,"b_sell":0,"c_buy":0,"c_sell":0 }
,{ "nse_code":"PEL","nse_name":"Piramal Enterprises Limited","last_p":2852.9,"v52_hi":3088.95,"v52_lo":1445,"v6_rate":3024.07,"v10_rate":3138.19,"v12_rate":3195.25,"v_time6":3,"v_time10":0,"v_time12":0,"close":2852.9,"last_pr":58.53,"rise_count":8,"drop_count":4,"avg_m_rise":4.29,"v_m1":"Ja","v_low1":1673.85,"v_high1":1859.45,"v_m2":"Fb","v_low2":1661,"v_high2":1910,"v_m3":"Ma","v_low3":1810.95,"v_high3":1948,"v_m4":"Ap","v_low4":1899.05,"v_high4":2534,"v_m5":"My","v_low5":2457,"v_high5":2949.9,"v_m6":"Jn","v_low6":2725.55,"v_high6":3089,"v_m7":"Ju","v_low7":2775,"v_high7":3050,"v_m8":"Ag","v_low8":2536,"v_high8":3027,"v_m9":"Sp","v_low9":2550.65,"v_high9":2930.3,"v_m10":"Oc","v_low10":2606.25,"v_high10":2820,"v_m11":"Nv","v_low11":2551.15,"v_high11":2819.9,"v_m12":"Dc","v_low12":2615.55,"v_high12":2947.75,"a_buy":0,"a_sell":0,"b_buy":0,"b_sell":0,"c_buy":0,"c_sell":0 }
,{ "nse_code":"DIVISLAB","nse_name":"Divi's Laboratories Limited","last_p":1059.8,"v52_hi":1163.45,"v52_lo":532.65,"v6_rate":1123.39,"v10_rate":1165.78,"v12_rate":1186.98,"v_time6":0,"v_time10":0,"v_time12":0,"close":1059.8,"last_pr":43.1,"rise_count":7,"drop_count":5,"avg_m_rise":4.07,"v_m1":"Ja","v_low1":671.5,"v_high1":756,"v_m2":"Fb","v_low2":685.05,"v_high2":779,"v_m3":"Ma","v_low3":611.45,"v_high3":795,"v_m4":"Ap","v_low4":606,"v_high4":664.15,"v_m5":"My","v_low5":532.65,"v_high5":644.7,"v_m6":"Jn","v_low6":582.8,"v_high6":664,"v_m7":"Ju","v_low7":647.55,"v_high7":760.8,"v_m8":"Ag","v_low8":611,"v_high8":709.9,"v_m9":"Sp","v_low9":692.55,"v_high9":1004.35,"v_m10":"Oc","v_low10":850.25,"v_high10":894.5,"v_m11":"Nv","v_low11":882,"v_high11":1117.6,"v_m12":"Dc","v_low12":999.05,"v_high12":1081.85,"a_buy":0,"a_sell":0,"b_buy":0,"b_sell":0,"c_buy":0,"c_sell":0 }
,{ "nse_code":"IBULHSGFIN","nse_name":"Indiabulls Housing Finance Limited","last_p":1194.8,"v52_hi":1373.95,"v52_lo":616.55,"v6_rate":1266.49,"v10_rate":1314.28,"v12_rate":1338.18,"v_time6":2,"v_time10":2,"v_time12":1,"close":1194.8,"last_pr":56.92,"rise_count":10,"drop_count":2,"avg_m_rise":4.02,"v_m1":"Ja","v_low1":741.25,"v_high1":780,"v_m2":"Fb","v_low2":750.55,"v_high2":882.5,"v_m3":"Ma","v_low3":833.4,"v_high3":1001.9,"v_m4":"Ap","v_low4":920,"v_high4":1040,"v_m5":"My","v_low5":1013.3,"v_high5":1164.35,"v_m6":"Jn","v_low6":1060.55,"v_high6":1187,"v_m7":"Ju","v_low7":1035.3,"v_high7":1216.5,"v_m8":"Ag","v_low8":1056.5,"v_high8":1237.95,"v_m9":"Sp","v_low9":1155,"v_high9":1336.95,"v_m10":"Oc","v_low10":1206.1,"v_high10":1373.95,"v_m11":"Nv","v_low11":1146.55,"v_high11":1251.15,"v_m12":"Dc","v_low12":1132.3,"v_high12":1224,"a_buy":0,"a_sell":0,"b_buy":0,"b_sell":0,"c_buy":0,"c_sell":0 }
,{ "nse_code":"BRITANNIA","nse_name":"Britannia Industries Limited","last_p":4745.4,"v52_hi":4963.9,"v52_lo":2772.85,"v6_rate":5030.12,"v10_rate":5219.94,"v12_rate":5314.85,"v_time6":0,"v_time10":0,"v_time12":0,"close":4745.4,"last_pr":56.99,"rise_count":11,"drop_count":1,"avg_m_rise":3.88,"v_m1":"Ja","v_low1":2923,"v_high1":3162,"v_m2":"Fb","v_low2":3112.75,"v_high2":3296,"v_m3":"Ma","v_low3":3045.3,"v_high3":3432.95,"v_m4":"Ap","v_low4":3272.8,"v_high4":3639,"v_m5":"My","v_low5":3371.5,"v_high5":3799.5,"v_m6":"Jn","v_low6":3523,"v_high6":3714,"v_m7":"Ju","v_low7":3656.05,"v_high7":3956.6,"v_m8":"Ag","v_low8":3830,"v_high8":4339.85,"v_m9":"Sp","v_low9":4151,"v_high9":4409,"v_m10":"Oc","v_low10":4302.3,"v_high10":4770,"v_m11":"Nv","v_low11":4584.8,"v_high11":4926.6,"v_m12":"Dc","v_low12":4598.4,"v_high12":4963.9,"a_buy":0,"a_sell":0,"b_buy":0,"b_sell":0,"c_buy":0,"c_sell":0 }
,{ "nse_code":"HINDUNILVR","nse_name":"Hindustan Unilever Limited","last_p":1362.65,"v52_hi":1367.95,"v52_lo":781.95,"v6_rate":1444.41,"v10_rate":1498.92,"v12_rate":1526.17,"v_time6":0,"v_time10":0,"v_time12":0,"close":1362.65,"last_pr":56.17,"rise_count":11,"drop_count":1,"avg_m_rise":3.84,"v_m1":"Ja","v_low1":822.45,"v_high1":875.95,"v_m2":"Fb","v_low2":837.5,"v_high2":872,"v_m3":"Ma","v_low3":862.2,"v_high3":923.8,"v_m4":"Ap","v_low4":898.55,"v_high4":951,"v_m5":"My","v_low5":922.6,"v_high5":1077,"v_m6":"Jn","v_low6":1046.1,"v_high6":1129,"v_m7":"Ju","v_low7":1081.1,"v_high7":1195.05,"v_m8":"Ag","v_low8":1143.55,"v_high8":1222.8,"v_m9":"Sp","v_low9":1169,"v_high9":1287.6,"v_m10":"Oc","v_low10":1171,"v_high10":1288.65,"v_m11":"Nv","v_low11":1226.35,"v_high11":1315,"v_m12":"Dc","v_low12":1241.2,"v_high12":1367.95,"a_buy":0,"a_sell":0,"b_buy":0,"b_sell":0,"c_buy":0,"c_sell":0 }
,{ "nse_code":"MCDOWELL-N","nse_name":"United Spirits Limited","last_p":3509.5,"v52_hi":3529,"v52_lo":1819.95,"v6_rate":3720.07,"v10_rate":3860.45,"v12_rate":3930.64,"v_time6":0,"v_time10":0,"v_time12":0,"close":3509.5,"last_pr":51.58,"rise_count":9,"drop_count":3,"avg_m_rise":3.81,"v_m1":"Ja","v_low1":1910,"v_high1":2328.1,"v_m2":"Fb","v_low2":2130.8,"v_high2":2427.7,"v_m3":"Ma","v_low3":2114.2,"v_high3":2377.2,"v_m4":"Ap","v_low4":1830.35,"v_high4":2079.5,"v_m5":"My","v_low5":1876,"v_high5":2327,"v_m6":"Jn","v_low6":2200,"v_high6":2519,"v_m7":"Ju","v_low7":2360.5,"v_high7":2774,"v_m8":"Ag","v_low8":2415,"v_high8":2659.8,"v_m9":"Sp","v_low9":2390,"v_high9":2722.95,"v_m10":"Oc","v_low10":2340.05,"v_high10":3176.7,"v_m11":"Nv","v_low11":2970.8,"v_high11":3403.2,"v_m12":"Dc","v_low12":3171,"v_high12":3529,"a_buy":0,"a_sell":0,"b_buy":0,"b_sell":0,"c_buy":0,"c_sell":0 }
,{ "nse_code":"SRTRANSFIN","nse_name":"Shriram Transport Finance Company Limited","last_p":1435,"v52_hi":1462.8,"v52_lo":778.05,"v6_rate":1521.1,"v10_rate":1578.5,"v12_rate":1607.2,"v_time6":0,"v_time10":0,"v_time12":0,"close":1435,"last_pr":46.77,"rise_count":8,"drop_count":4,"avg_m_rise":3.57,"v_m1":"Ja","v_low1":905,"v_high1":996.65,"v_m2":"Fb","v_low2":925,"v_high2":985,"v_m3":"Ma","v_low3":888.2,"v_high3":1090,"v_m4":"Ap","v_low4":1015.8,"v_high4":1119.5,"v_m5":"My","v_low5":933.8,"v_high5":1046.45,"v_m6":"Jn","v_low6":945,"v_high6":1039,"v_m7":"Ju","v_low7":953.75,"v_high7":1198.65,"v_m8":"Ag","v_low8":917.7,"v_high8":1042,"v_m9":"Sp","v_low9":968.45,"v_high9":1115,"v_m10":"Oc","v_low10":1040.1,"v_high10":1203.3,"v_m11":"Nv","v_low11":1167.25,"v_high11":1364.6,"v_m12":"Dc","v_low12":1282,"v_high12":1462.8,"a_buy":0,"a_sell":0,"b_buy":0,"b_sell":0,"c_buy":0,"c_sell":0 }
,{ "nse_code":"PNB","nse_name":"Punjab National Bank","last_p":170.5,"v52_hi":231.45,"v52_lo":112,"v6_rate":180.73,"v10_rate":187.55,"v12_rate":190.96,"v_time6":4,"v_time10":2,"v_time12":2,"close":170.5,"last_pr":28.51,"rise_count":6,"drop_count":6,"avg_m_rise":3.53,"v_m1":"Ja","v_low1":124,"v_high1":140.85,"v_m2":"Fb","v_low2":134.65,"v_high2":155.7,"v_m3":"Ma","v_low3":135.35,"v_high3":154,"v_m4":"Ap","v_low4":148.55,"v_high4":170.7,"v_m5":"My","v_low5":142.4,"v_high5":185.8,"v_m6":"Jn","v_low6":132.65,"v_high6":155,"v_m7":"Ju","v_low7":135.25,"v_high7":164.3,"v_m8":"Ag","v_low8":135.65,"v_high8":164.2,"v_m9":"Sp","v_low9":128.4,"v_high9":147.3,"v_m10":"Oc","v_low10":128.2,"v_high10":231.45,"v_m11":"Nv","v_low11":175.35,"v_high11":212,"v_m12":"Dc","v_low12":161.85,"v_high12":181,"a_buy":0,"a_sell":0,"b_buy":0,"b_sell":0,"c_buy":0,"c_sell":0 }
,{ "nse_code":"TATASTEEL","nse_name":"Tata Steel Limited","last_p":702.8,"v52_hi":735,"v52_lo":377.35,"v6_rate":744.97,"v10_rate":773.08,"v12_rate":787.14,"v_time6":0,"v_time10":0,"v_time12":0,"close":702.8,"last_pr":50.37,"rise_count":9,"drop_count":3,"avg_m_rise":3.53,"v_m1":"Ja","v_low1":443.25,"v_high1":476.75,"v_m2":"Fb","v_low2":455.65,"v_high2":495.9,"v_m3":"Ma","v_low3":462.2,"v_high3":508.75,"v_m4":"Ap","v_low4":442.05,"v_high4":506.35,"v_m5":"My","v_low5":428,"v_high5":520.65,"v_m6":"Jn","v_low6":487,"v_high6":548,"v_m7":"Ju","v_low7":542.05,"v_high7":572.35,"v_m8":"Ag","v_low8":557.55,"v_high8":643,"v_m9":"Sp","v_low9":623.1,"v_high9":696.25,"v_m10":"Oc","v_low10":654.45,"v_high10":735,"v_m11":"Nv","v_low11":669.25,"v_high11":718.5,"v_m12":"Dc","v_low12":660.7,"v_high12":716.9,"a_buy":0,"a_sell":0,"b_buy":0,"b_sell":0,"c_buy":0,"c_sell":0 }
,{ "nse_code":"BHARTIARTL","nse_name":"Bharti Airtel Limited","last_p":528.9,"v52_hi":564.8,"v52_lo":288.7,"v6_rate":560.63,"v10_rate":581.79,"v12_rate":592.37,"v_time6":1,"v_time10":0,"v_time12":0,"close":528.9,"last_pr":46.2,"rise_count":8,"drop_count":4,"avg_m_rise":3.48,"v_m1":"Ja","v_low1":305,"v_high1":369.95,"v_m2":"Fb","v_low2":340.15,"v_high2":401,"v_m3":"Ma","v_low3":325.8,"v_high3":369.8,"v_m4":"Ap","v_low4":332.75,"v_high4":361.95,"v_m5":"My","v_low5":336.5,"v_high5":381.6,"v_m6":"Jn","v_low6":360.6,"v_high6":386,"v_m7":"Ju","v_low7":363.8,"v_high7":431.6,"v_m8":"Ag","v_low8":403.75,"v_high8":438.15,"v_m9":"Sp","v_low9":371,"v_high9":430.45,"v_m10":"Oc","v_low10":373.15,"v_high10":519.35,"v_m11":"Nv","v_low11":481.15,"v_high11":564.8,"v_m12":"Dc","v_low12":476.85,"v_high12":540.85,"a_buy":0,"a_sell":0,"b_buy":0,"b_sell":0,"c_buy":0,"c_sell":0 }
,{ "nse_code":"HDFCBANK","nse_name":"HDFC Bank Limited","last_p":1868.15,"v52_hi":1903.1,"v52_lo":1168.4,"v6_rate":1980.24,"v10_rate":2054.97,"v12_rate":2092.33,"v_time6":0,"v_time10":0,"v_time12":0,"close":1868.15,"last_pr":46.39,"rise_count":11,"drop_count":1,"avg_m_rise":3.28,"v_m1":"Ja","v_low1":1230,"v_high1":1300,"v_m2":"Fb","v_low2":1280.5,"v_high2":1454,"v_m3":"Ma","v_low3":1369,"v_high3":1479.95,"v_m4":"Ap","v_low4":1425.05,"v_high4":1573.95,"v_m5":"My","v_low5":1522.6,"v_high5":1648,"v_m6":"Jn","v_low6":1620.55,"v_high6":1716,"v_m7":"Ju","v_low7":1645,"v_high7":1798.8,"v_m8":"Ag","v_low8":1731.15,"v_high8":1809.15,"v_m9":"Sp","v_low9":1738,"v_high9":1868,"v_m10":"Oc","v_low10":1757.85,"v_high10":1879.6,"v_m11":"Nv","v_low11":1788,"v_high11":1875.5,"v_m12":"Dc","v_low12":1799,"v_high12":1903.1,"a_buy":0,"a_sell":0,"b_buy":0,"b_sell":0,"c_buy":0,"c_sell":0 }
,{ "nse_code":"PGHH","nse_name":"Procter & Gamble Hygiene and Health Care Limited","last_p":9447.2,"v52_hi":9900,"v52_lo":6500,"v6_rate":10014.03,"v10_rate":10391.92,"v12_rate":10580.86,"v_time6":0,"v_time10":0,"v_time12":0,"close":9447.2,"last_pr":39.67,"rise_count":8,"drop_count":4,"avg_m_rise":2.89,"v_m1":"Ja","v_low1":6700.1,"v_high1":7087.95,"v_m2":"Fb","v_low2":6865.2,"v_high2":7150,"v_m3":"Ma","v_low3":6611.15,"v_high3":7635.7,"v_m4":"Ap","v_low4":7260.25,"v_high4":7635,"v_m5":"My","v_low5":7316,"v_high5":8199,"v_m6":"Jn","v_low6":7460.05,"v_high6":8167,"v_m7":"Ju","v_low7":7925.7,"v_high7":8387,"v_m8":"Ag","v_low8":7851.5,"v_high8":8345,"v_m9":"Sp","v_low9":8131.05,"v_high9":8865.8,"v_m10":"Oc","v_low10":8388,"v_high10":8747,"v_m11":"Nv","v_low11":8639.05,"v_high11":9600,"v_m12":"Dc","v_low12":9239.1,"v_high12":9900,"a_buy":0,"a_sell":0,"b_buy":0,"b_sell":0,"c_buy":0,"c_sell":0 }
,{ "nse_code":"SAIL","nse_name":"Steel Authority of India Limited","last_p":84.55,"v52_hi":87.8,"v52_lo":47.1,"v6_rate":89.62,"v10_rate":93.01,"v12_rate":94.7,"v_time6":0,"v_time10":0,"v_time12":0,"close":84.55,"last_pr":31.16,"rise_count":6,"drop_count":6,"avg_m_rise":2.69,"v_m1":"Ja","v_low1":57,"v_high1":65.3,"v_m2":"Fb","v_low2":58.1,"v_high2":68.15,"v_m3":"Ma","v_low3":58.75,"v_high3":64.65,"v_m4":"Ap","v_low4":59.4,"v_high4":68.6,"v_m5":"My","v_low5":56.25,"v_high5":63.25,"v_m6":"Jn","v_low6":55.5,"v_high6":59,"v_m7":"Ju","v_low7":58.1,"v_high7":65,"v_m8":"Ag","v_low8":55.2,"v_high8":64.8,"v_m9":"Sp","v_low9":52.85,"v_high9":64.45,"v_m10":"Oc","v_low10":53.4,"v_high10":83.25,"v_m11":"Nv","v_low11":74.9,"v_high11":87.8,"v_m12":"Dc","v_low12":74.75,"v_high12":85.65,"a_buy":0,"a_sell":0,"b_buy":0,"b_sell":0,"c_buy":0,"c_sell":0 }
,{ "nse_code":"ADANIPORTS","nse_name":"Adani Ports and Special Economic Zone Limited","last_p":404.4,"v52_hi":443.3,"v52_lo":257.25,"v6_rate":428.66,"v10_rate":444.84,"v12_rate":452.93,"v_time6":2,"v_time10":0,"v_time12":0,"close":404.4,"last_pr":34.16,"rise_count":10,"drop_count":2,"avg_m_rise":2.56,"v_m1":"Ja","v_low1":283.4,"v_high1":308.95,"v_m2":"Fb","v_low2":293.65,"v_high2":315.9,"v_m3":"Ma","v_low3":291,"v_high3":342.7,"v_m4":"Ap","v_low4":317.6,"v_high4":359.25,"v_m5":"My","v_low5":323.9,"v_high5":362.55,"v_m6":"Jn","v_low6":337.6,"v_high6":378,"v_m7":"Ju","v_low7":359.5,"v_high7":398.45,"v_m8":"Ag","v_low8":369.65,"v_high8":421.5,"v_m9":"Sp","v_low9":363.7,"v_high9":414.7,"v_m10":"Oc","v_low10":375.1,"v_high10":439,"v_m11":"Nv","v_low11":395,"v_high11":443.3,"v_m12":"Dc","v_low12":374.05,"v_high12":414.5,"a_buy":0,"a_sell":0,"b_buy":0,"b_sell":0,"c_buy":0,"c_sell":0 }
,{ "nse_code":"HINDALCO","nse_name":"Hindalco Industries Limited","last_p":258.35,"v52_hi":278.55,"v52_lo":147.85,"v6_rate":273.85,"v10_rate":284.19,"v12_rate":289.35,"v_time6":2,"v_time10":0,"v_time12":0,"close":258.35,"last_pr":33.64,"rise_count":9,"drop_count":3,"avg_m_rise":2.55,"v_m1":"Ja","v_low1":169.3,"v_high1":195.3,"v_m2":"Fb","v_low2":179.1,"v_high2":200,"v_m3":"Ma","v_low3":184.6,"v_high3":202.3,"v_m4":"Ap","v_low4":179.35,"v_high4":203.7,"v_m5":"My","v_low5":181.6,"v_high5":210.35,"v_m6":"Jn","v_low6":185.1,"v_high6":204,"v_m7":"Ju","v_low7":182.6,"v_high7":223.75,"v_m8":"Ag","v_low8":218,"v_high8":244.9,"v_m9":"Sp","v_low9":223.3,"v_high9":255.45,"v_m10":"Oc","v_low10":238.2,"v_high10":278.55,"v_m11":"Nv","v_low11":239.5,"v_high11":277.6,"v_m12":"Dc","v_low12":229.4,"v_high12":261,"a_buy":0,"a_sell":0,"b_buy":0,"b_sell":0,"c_buy":0,"c_sell":0 }
,{ "nse_code":"ASHOKLEY","nse_name":"Ashok Leyland Limited","last_p":117.8,"v52_hi":133.9,"v52_lo":75.05,"v6_rate":124.87,"v10_rate":129.58,"v12_rate":131.94,"v_time6":2,"v_time10":2,"v_time12":2,"close":117.8,"last_pr":32.26,"rise_count":8,"drop_count":4,"avg_m_rise":2.54,"v_m1":"Ja","v_low1":84.05,"v_high1":93.15,"v_m2":"Fb","v_low2":88.65,"v_high2":97,"v_m3":"Ma","v_low3":80.75,"v_high3":93.4,"v_m4":"Ap","v_low4":81.05,"v_high4":88.85,"v_m5":"My","v_low5":81.5,"v_high5":95.9,"v_m6":"Jn","v_low6":90,"v_high6":97,"v_m7":"Ju","v_low7":93.55,"v_high7":110.5,"v_m8":"Ag","v_low8":98.6,"v_high8":114.35,"v_m9":"Sp","v_low9":107.2,"v_high9":123.9,"v_m10":"Oc","v_low10":121.25,"v_high10":133.9,"v_m11":"Nv","v_low11":107.7,"v_high11":132.8,"v_m12":"Dc","v_low12":105.95,"v_high12":123.2,"a_buy":0,"a_sell":0,"b_buy":0,"b_sell":0,"c_buy":0,"c_sell":0 }
,{ "nse_code":"INDUSINDBK","nse_name":"IndusInd Bank Limited","last_p":1660.9,"v52_hi":1804,"v52_lo":1037,"v6_rate":1760.55,"v10_rate":1826.99,"v12_rate":1860.21,"v_time6":1,"v_time10":0,"v_time12":0,"close":1660.9,"last_pr":33.75,"rise_count":10,"drop_count":2,"avg_m_rise":2.52,"v_m1":"Ja","v_low1":1202,"v_high1":1269,"v_m2":"Fb","v_low2":1246,"v_high2":1365.85,"v_m3":"Ma","v_low3":1287.55,"v_high3":1431,"v_m4":"Ap","v_low4":1393.05,"v_high4":1483.45,"v_m5":"My","v_low5":1375.2,"v_high5":1504.7,"v_m6":"Jn","v_low6":1462.3,"v_high6":1538,"v_m7":"Ju","v_low7":1472.75,"v_high7":1650.8,"v_m8":"Ag","v_low8":1594.3,"v_high8":1684,"v_m9":"Sp","v_low9":1641.2,"v_high9":1804,"v_m10":"Oc","v_low10":1572.4,"v_high10":1758,"v_m11":"Nv","v_low11":1592.5,"v_high11":1692,"v_m12":"Dc","v_low12":1630.2,"v_high12":1697.3,"a_buy":0,"a_sell":0,"b_buy":0,"b_sell":0,"c_buy":0,"c_sell":0 }
,{ "nse_code":"UBL","nse_name":"United Breweries Limited","last_p":1073.05,"v52_hi":1190.4,"v52_lo":717.2,"v6_rate":1137.43,"v10_rate":1180.36,"v12_rate":1201.82,"v_time6":1,"v_time10":1,"v_time12":0,"close":1073.05,"last_pr":29.64,"rise_count":6,"drop_count":6,"avg_m_rise":2.51,"v_m1":"Ja","v_low1":796.3,"v_high1":846.9,"v_m2":"Fb","v_low2":773.1,"v_high2":845,"v_m3":"Ma","v_low3":763.7,"v_high3":798,"v_m4":"Ap","v_low4":717.2,"v_high4":786,"v_m5":"My","v_low5":763.25,"v_high5":878.4,"v_m6":"Jn","v_low6":772.65,"v_high6":845,"v_m7":"Ju","v_low7":780.15,"v_high7":842.45,"v_m8":"Ag","v_low8":778.7,"v_high8":859,"v_m9":"Sp","v_low9":775.25,"v_high9":867,"v_m10":"Oc","v_low10":822.8,"v_high10":1063.45,"v_m11":"Nv","v_low11":1015,"v_high11":1190.4,"v_m12":"Dc","v_low12":991.3,"v_high12":1097.95,"a_buy":0,"a_sell":0,"b_buy":0,"b_sell":0,"c_buy":0,"c_sell":0 }
,{ "nse_code":"JSWSTEEL","nse_name":"JSW Steel Limited","last_p":262.1,"v52_hi":1653.6,"v52_lo":160.6,"v6_rate":277.83,"v10_rate":288.31,"v12_rate":293.55,"v_time6":0,"v_time10":0,"v_time12":0,"close":262.1,"last_pr":31.33,"rise_count":7,"drop_count":5,"avg_m_rise":2.43,"v_m1":"Ja","v_low1":184.6,"v_high1":201.4,"v_m2":"Fb","v_low2":178.3,"v_high2":199.65,"v_m3":"Ma","v_low3":175.15,"v_high3":195.9,"v_m4":"Ap","v_low4":185.2,"v_high4":207,"v_m5":"My","v_low5":184.1,"v_high5":209.45,"v_m6":"Jn","v_low6":189.3,"v_high6":209,"v_m7":"Ju","v_low7":200,"v_high7":221.95,"v_m8":"Ag","v_low8":215.2,"v_high8":260.3,"v_m9":"Sp","v_low9":229.5,"v_high9":271.8,"v_m10":"Oc","v_low10":244.25,"v_high10":269.65,"v_m11":"Nv","v_low11":253.1,"v_high11":274.5,"v_m12":"Dc","v_low12":237.6,"v_high12":264.5,"a_buy":0,"a_sell":0,"b_buy":0,"b_sell":0,"c_buy":0,"c_sell":0 }
,{ "nse_code":"EICHERMOT","nse_name":"Eicher Motors Limited","last_p":30174.6,"v52_hi":33480,"v52_lo":20228,"v6_rate":31985.08,"v10_rate":33192.06,"v12_rate":33795.55,"v_time6":4,"v_time10":1,"v_time12":0,"close":30174.6,"last_pr":30.74,"rise_count":9,"drop_count":3,"avg_m_rise":2.37,"v_m1":"Ja","v_low1":22175.05,"v_high1":23710.65,"v_m2":"Fb","v_low2":23050,"v_high2":25550,"v_m3":"Ma","v_low3":22997.5,"v_high3":25814.9,"v_m4":"Ap","v_low4":25321.1,"v_high4":26500,"v_m5":"My","v_low5":25336.8,"v_high5":30051,"v_m6":"Jn","v_low6":26400,"v_high6":30051,"v_m7":"Ju","v_low7":27119,"v_high7":30200,"v_m8":"Ag","v_low8":29135.4,"v_high8":32449.35,"v_m9":"Sp","v_low9":29910.05,"v_high9":33480,"v_m10":"Oc","v_low10":30712.3,"v_high10":32766.6,"v_m11":"Nv","v_low11":29612,"v_high11":32539.2,"v_m12":"Dc","v_low12":28111,"v_high12":30999,"a_buy":0,"a_sell":0,"b_buy":0,"b_sell":0,"c_buy":0,"c_sell":0 }
,{ "nse_code":"INDIGO","nse_name":"InterGlobe Aviation Limited","last_p":1166.3,"v52_hi":1346.7,"v52_lo":811.65,"v6_rate":1236.28,"v10_rate":1282.93,"v12_rate":1306.26,"v_time6":6,"v_time10":3,"v_time12":2,"close":1166.3,"last_pr":27.01,"rise_count":7,"drop_count":5,"avg_m_rise":2.35,"v_m1":"Ja","v_low1":873,"v_high1":944,"v_m2":"Fb","v_low2":815,"v_high2":877,"v_m3":"Ma","v_low3":852.1,"v_high3":1094,"v_m4":"Ap","v_low4":1022.6,"v_high4":1168.7,"v_m5":"My","v_low5":1004,"v_high5":1152,"v_m6":"Jn","v_low6":1100,"v_high6":1275,"v_m7":"Ju","v_low7":1157.95,"v_high7":1317.2,"v_m8":"Ag","v_low8":1161.55,"v_high8":1346.7,"v_m9":"Sp","v_low9":1022,"v_high9":1274,"v_m10":"Oc","v_low10":1076.4,"v_high10":1252,"v_m11":"Nv","v_low11":1115.5,"v_high11":1298.7,"v_m12":"Dc","v_low12":1114.25,"v_high12":1199,"a_buy":0,"a_sell":0,"b_buy":0,"b_sell":0,"c_buy":0,"c_sell":0 }
,{ "nse_code":"PIDILITIND","nse_name":"Pidilite Industries Limited","last_p":889.9,"v52_hi":916.9,"v52_lo":567.75,"v6_rate":943.29,"v10_rate":978.89,"v12_rate":996.69,"v_time6":0,"v_time10":0,"v_time12":0,"close":889.9,"last_pr":30.71,"rise_count":10,"drop_count":2,"avg_m_rise":2.32,"v_m1":"Ja","v_low1":624.1,"v_high1":701.5,"v_m2":"Fb","v_low2":662.2,"v_high2":712,"v_m3":"Ma","v_low3":665.05,"v_high3":712,"v_m4":"Ap","v_low4":695.55,"v_high4":738,"v_m5":"My","v_low5":716,"v_high5":782.8,"v_m6":"Jn","v_low6":762,"v_high6":839,"v_m7":"Ju","v_low7":781.05,"v_high7":834.95,"v_m8":"Ag","v_low8":775.3,"v_high8":843.7,"v_m9":"Sp","v_low9":775,"v_high9":868.45,"v_m10":"Oc","v_low10":780,"v_high10":820.95,"v_m11":"Nv","v_low11":751.3,"v_high11":859,"v_m12":"Dc","v_low12":825,"v_high12":916.9,"a_buy":0,"a_sell":0,"b_buy":0,"b_sell":0,"c_buy":0,"c_sell":0 }
,{ "nse_code":"HAVELLS","nse_name":"Havells India Limited","last_p":558.6,"v52_hi":564.6,"v52_lo":310.55,"v6_rate":592.12,"v10_rate":614.46,"v12_rate":625.63,"v_time6":0,"v_time10":0,"v_time12":0,"close":558.6,"last_pr":30,"rise_count":9,"drop_count":3,"avg_m_rise":2.32,"v_m1":"Ja","v_low1":365.4,"v_high1":432.2,"v_m2":"Fb","v_low2":396.25,"v_high2":446,"v_m3":"Ma","v_low3":405.6,"v_high3":474.5,"v_m4":"Ap","v_low4":459.2,"v_high4":499.45,"v_m5":"My","v_low5":433.6,"v_high5":526.3,"v_m6":"Jn","v_low6":440.85,"v_high6":512,"v_m7":"Ju","v_low7":451.3,"v_high7":485.55,"v_m8":"Ag","v_low8":453.85,"v_high8":501.9,"v_m9":"Sp","v_low9":469.55,"v_high9":521.45,"v_m10":"Oc","v_low10":479.5,"v_high10":564.6,"v_m11":"Nv","v_low11":486.05,"v_high11":527.9,"v_m12":"Dc","v_low12":502.6,"v_high12":561.85,"a_buy":0,"a_sell":0,"b_buy":0,"b_sell":0,"c_buy":0,"c_sell":0 }
,{ "nse_code":"KOTAKBANK","nse_name":"Kotak Mahindra Bank Limited","last_p":1012.7,"v52_hi":1115.05,"v52_lo":692.5,"v6_rate":1073.46,"v10_rate":1113.97,"v12_rate":1134.22,"v_time6":1,"v_time10":1,"v_time12":0,"close":1012.7,"last_pr":29.41,"rise_count":9,"drop_count":3,"avg_m_rise":2.24,"v_m1":"Ja","v_low1":718,"v_high1":802.1,"v_m2":"Fb","v_low2":739.15,"v_high2":814.4,"v_m3":"Ma","v_low3":802.05,"v_high3":886.4,"v_m4":"Ap","v_low4":867.2,"v_high4":921,"v_m5":"My","v_low5":900,"v_high5":981.45,"v_m6":"Jn","v_low6":936,"v_high6":1005,"v_m7":"Ju","v_low7":940.2,"v_high7":1031.7,"v_m8":"Ag","v_low8":962,"v_high8":1024,"v_m9":"Sp","v_low9":968,"v_high9":1045.4,"v_m10":"Oc","v_low10":985.15,"v_high10":1115.05,"v_m11":"Nv","v_low11":982.55,"v_high11":1050,"v_m12":"Dc","v_low12":992.5,"v_high12":1038,"a_buy":0,"a_sell":0,"b_buy":0,"b_sell":0,"c_buy":0,"c_sell":0 }
,{ "nse_code":"GSKCONS","nse_name":"GlaxoSmithKline Consumer Healthcare Limited","last_p":6493.25,"v52_hi":6573.7,"v52_lo":4851,"v6_rate":6882.85,"v10_rate":7142.58,"v12_rate":7272.44,"v_time6":0,"v_time10":0,"v_time12":0,"close":6493.25,"last_pr":24.31,"rise_count":8,"drop_count":4,"avg_m_rise":2.06,"v_m1":"Ja","v_low1":4980,"v_high1":5288,"v_m2":"Fb","v_low2":5015,"v_high2":5249,"v_m3":"Ma","v_low3":5060,"v_high3":5575.95,"v_m4":"Ap","v_low4":5035.6,"v_high4":5349.8,"v_m5":"My","v_low5":5105,"v_high5":5398,"v_m6":"Jn","v_low6":5270.05,"v_high6":5469,"v_m7":"Ju","v_low7":5350,"v_high7":5577,"v_m8":"Ag","v_low8":5251,"v_high8":5786,"v_m9":"Sp","v_low9":4851,"v_high9":5399.95,"v_m10":"Oc","v_low10":4897.5,"v_high10":5097.75,"v_m11":"Nv","v_low11":5109.95,"v_high11":6165.05,"v_m12":"Dc","v_low12":6001,"v_high12":6573.7,"a_buy":0,"a_sell":0,"b_buy":0,"b_sell":0,"c_buy":0,"c_sell":0 }
,{ "nse_code":"HDFC","nse_name":"Housing Development Finance Corporation Limited","last_p":1693.7,"v52_hi":1804,"v52_lo":1197.25,"v6_rate":1795.32,"v10_rate":1863.07,"v12_rate":1896.94,"v_time6":4,"v_time10":0,"v_time12":0,"close":1693.7,"last_pr":25.44,"rise_count":9,"drop_count":3,"avg_m_rise":1.95,"v_m1":"Ja","v_low1":1230.6,"v_high1":1388.2,"v_m2":"Fb","v_low2":1368.1,"v_high2":1432.65,"v_m3":"Ma","v_low3":1361.3,"v_high3":1531,"v_m4":"Ap","v_low4":1460,"v_high4":1590,"v_m5":"My","v_low5":1503.45,"v_high5":1604,"v_m6":"Jn","v_low6":1551.8,"v_high6":1682,"v_m7":"Ju","v_low7":1580.3,"v_high7":1799.9,"v_m8":"Ag","v_low8":1681.4,"v_high8":1799,"v_m9":"Sp","v_low9":1713,"v_high9":1802,"v_m10":"Oc","v_low10":1638,"v_high10":1779.4,"v_m11":"Nv","v_low11":1648.4,"v_high11":1804,"v_m12":"Dc","v_low12":1640.85,"v_high12":1741.3,"a_buy":0,"a_sell":0,"b_buy":0,"b_sell":0,"c_buy":0,"c_sell":0 }
,{ "nse_code":"EMAMILTD","nse_name":"Emami Limited","last_p":1330.6,"v52_hi":1351.55,"v52_lo":935.4,"v6_rate":1410.44,"v10_rate":1463.66,"v12_rate":1490.27,"v_time6":0,"v_time10":0,"v_time12":0,"close":1330.6,"last_pr":24.11,"rise_count":9,"drop_count":3,"avg_m_rise":1.94,"v_m1":"Ja","v_low1":981.65,"v_high1":1089,"v_m2":"Fb","v_low2":1013.95,"v_high2":1199,"v_m3":"Ma","v_low3":990,"v_high3":1086.05,"v_m4":"Ap","v_low4":998.3,"v_high4":1085,"v_m5":"My","v_low5":1035,"v_high5":1154.4,"v_m6":"Jn","v_low6":1001,"v_high6":1155,"v_m7":"Ju","v_low7":1046.7,"v_high7":1198,"v_m8":"Ag","v_low8":1019.75,"v_high8":1168.25,"v_m9":"Sp","v_low9":1080,"v_high9":1194.8,"v_m10":"Oc","v_low10":1065.4,"v_high10":1285.25,"v_m11":"Nv","v_low11":1221.15,"v_high11":1339,"v_m12":"Dc","v_low12":1239,"v_high12":1351.55,"a_buy":0,"a_sell":0,"b_buy":0,"b_sell":0,"c_buy":0,"c_sell":0 }
,{ "nse_code":"SBIN","nse_name":"State Bank of India","last_p":317.5,"v52_hi":351.3,"v52_lo":241.1,"v6_rate":336.55,"v10_rate":349.25,"v12_rate":355.6,"v_time6":2,"v_time10":1,"v_time12":0,"close":317.5,"last_pr":20.62,"rise_count":8,"drop_count":4,"avg_m_rise":1.93,"v_m1":"Ja","v_low1":250.1,"v_high1":268.2,"v_m2":"Fb","v_low2":261.6,"v_high2":282.8,"v_m3":"Ma","v_low3":264.25,"v_high3":295,"v_m4":"Ap","v_low4":279.25,"v_high4":298.75,"v_m5":"My","v_low5":281.05,"v_high5":315.3,"v_m6":"Jn","v_low6":269.7,"v_high6":296,"v_m7":"Ju","v_low7":253,"v_high7":313.85,"v_m8":"Ag","v_low8":271.2,"v_high8":314.8,"v_m9":"Sp","v_low9":249.5,"v_high9":280.4,"v_m10":"Oc","v_low10":241.15,"v_high10":351.3,"v_m11":"Nv","v_low11":306.65,"v_high11":346.7,"v_m12":"Dc","v_low12":300.4,"v_high12":323.5,"a_buy":0,"a_sell":0,"b_buy":0,"b_sell":0,"c_buy":0,"c_sell":0 }
,{ "nse_code":"DABUR","nse_name":"Dabur India Limited","last_p":350.8,"v52_hi":360.85,"v52_lo":259.15,"v6_rate":371.85,"v10_rate":385.88,"v12_rate":392.9,"v_time6":0,"v_time10":0,"v_time12":0,"close":350.8,"last_pr":24.74,"rise_count":8,"drop_count":4,"avg_m_rise":1.91,"v_m1":"Ja","v_low1":273.6,"v_high1":284,"v_m2":"Fb","v_low2":263.6,"v_high2":278.7,"v_m3":"Ma","v_low3":271.2,"v_high3":286.4,"v_m4":"Ap","v_low4":277.2,"v_high4":295.95,"v_m5":"My","v_low5":265,"v_high5":288.5,"v_m6":"Jn","v_low6":277.5,"v_high6":295,"v_m7":"Ju","v_low7":291.4,"v_high7":313.6,"v_m8":"Ag","v_low8":296.5,"v_high8":323,"v_m9":"Sp","v_low9":298.7,"v_high9":318.5,"v_m10":"Oc","v_low10":306,"v_high10":334.6,"v_m11":"Nv","v_low11":329.7,"v_high11":360.85,"v_m12":"Dc","v_low12":325,"v_high12":354.25,"a_buy":0,"a_sell":0,"b_buy":0,"b_sell":0,"c_buy":0,"c_sell":0 }
,{ "nse_code":"ABB","nse_name":"ABB India Limited","last_p":1383.1,"v52_hi":1620,"v52_lo":1017.55,"v6_rate":1466.09,"v10_rate":1521.41,"v12_rate":1549.07,"v_time6":5,"v_time10":3,"v_time12":3,"close":1383.1,"last_pr":22.58,"rise_count":7,"drop_count":5,"avg_m_rise":1.89,"v_m1":"Ja","v_low1":1046.45,"v_high1":1160,"v_m2":"Fb","v_low2":1092.6,"v_high2":1265,"v_m3":"Ma","v_low3":1180,"v_high3":1292,"v_m4":"Ap","v_low4":1282.5,"v_high4":1484,"v_m5":"My","v_low5":1393.2,"v_high5":1620,"v_m6":"Jn","v_low6":1376,"v_high6":1559,"v_m7":"Ju","v_low7":1351.05,"v_high7":1549.65,"v_m8":"Ag","v_low8":1302,"v_high8":1440,"v_m9":"Sp","v_low9":1298.8,"v_high9":1493,"v_m10":"Oc","v_low10":1330,"v_high10":1422.7,"v_m11":"Nv","v_low11":1305.1,"v_high11":1448,"v_m12":"Dc","v_low12":1337,"v_high12":1421.95,"a_buy":0,"a_sell":0,"b_buy":0,"b_sell":0,"c_buy":0,"c_sell":0 }
,{ "nse_code":"ACC","nse_name":"ACC Limited","last_p":1727.2,"v52_hi":1869.95,"v52_lo":1272,"v6_rate":1830.83,"v10_rate":1899.92,"v12_rate":1934.46,"v_time6":4,"v_time10":0,"v_time12":0,"close":1727.2,"last_pr":23.22,"rise_count":7,"drop_count":5,"avg_m_rise":1.89,"v_m1":"Ja","v_low1":1315,"v_high1":1440,"v_m2":"Fb","v_low2":1402,"v_high2":1512.05,"v_m3":"Ma","v_low3":1380.4,"v_high3":1450,"v_m4":"Ap","v_low4":1453.15,"v_high4":1644.85,"v_m5":"My","v_low5":1570,"v_high5":1756.7,"v_m6":"Jn","v_low6":1541.25,"v_high6":1674,"v_m7":"Ju","v_low7":1563.3,"v_high7":1809,"v_m8":"Ag","v_low8":1712.5,"v_high8":1837.55,"v_m9":"Sp","v_low9":1580,"v_high9":1869.95,"v_m10":"Oc","v_low10":1633.6,"v_high10":1837,"v_m11":"Nv","v_low11":1662.05,"v_high11":1835,"v_m12":"Dc","v_low12":1655.5,"v_high12":1774.35,"a_buy":0,"a_sell":0,"b_buy":0,"b_sell":0,"c_buy":0,"c_sell":0 }
,{ "nse_code":"OFSS","nse_name":"Oracle Financial Services Software Limited","last_p":4041.55,"v52_hi":4165,"v52_lo":3085.5,"v6_rate":4284.04,"v10_rate":4445.71,"v12_rate":4526.54,"v_time6":0,"v_time10":0,"v_time12":0,"close":4041.55,"last_pr":23.12,"rise_count":7,"drop_count":5,"avg_m_rise":1.87,"v_m1":"Ja","v_low1":3193.05,"v_high1":3382.95,"v_m2":"Fb","v_low2":3280.65,"v_high2":3776.45,"v_m3":"Ma","v_low3":3585.95,"v_high3":4088,"v_m4":"Ap","v_low4":3509.9,"v_high4":3916.85,"v_m5":"My","v_low5":3476,"v_high5":3898,"v_m6":"Jn","v_low6":3516.6,"v_high6":3780,"v_m7":"Ju","v_low7":3537.4,"v_high7":3730,"v_m8":"Ag","v_low8":3372.25,"v_high8":3668.5,"v_m9":"Sp","v_low9":3414.2,"v_high9":3679.05,"v_m10":"Oc","v_low10":3460.7,"v_high10":3750,"v_m11":"Nv","v_low11":3499,"v_high11":3789,"v_m12":"Dc","v_low12":3659.95,"v_high12":4165,"a_buy":0,"a_sell":0,"b_buy":0,"b_sell":0,"c_buy":0,"c_sell":0 }
,{ "nse_code":"VEDL","nse_name":"Vedanta Limited","last_p":317.25,"v52_hi":346.4,"v52_lo":204.8,"v6_rate":336.29,"v10_rate":348.98,"v12_rate":355.32,"v_time6":2,"v_time10":0,"v_time12":0,"close":317.25,"last_pr":22.02,"rise_count":9,"drop_count":3,"avg_m_rise":1.87,"v_m1":"Ja","v_low1":235.2,"v_high1":261.8,"v_m2":"Fb","v_low2":242.85,"v_high2":274.6,"v_m3":"Ma","v_low3":247.25,"v_high3":278.1,"v_m4":"Ap","v_low4":226.5,"v_high4":277.5,"v_m5":"My","v_low5":217.75,"v_high5":248.45,"v_m6":"Jn","v_low6":226.5,"v_high6":253,"v_m7":"Ju","v_low7":250.4,"v_high7":283.7,"v_m8":"Ag","v_low8":276.6,"v_high8":310.25,"v_m9":"Sp","v_low9":297,"v_high9":334.65,"v_m10":"Oc","v_low10":310.15,"v_high10":345.2,"v_m11":"Nv","v_low11":294,"v_high11":346.4,"v_m12":"Dc","v_low12":277.65,"v_high12":319.45,"a_buy":0,"a_sell":0,"b_buy":0,"b_sell":0,"c_buy":0,"c_sell":0 }
,{ "nse_code":"MARICO","nse_name":"Marico Limited","last_p":319.05,"v52_hi":348.7,"v52_lo":238.05,"v6_rate":338.19,"v10_rate":350.96,"v12_rate":357.34,"v_time6":1,"v_time10":0,"v_time12":0,"close":319.05,"last_pr":22.6,"rise_count":9,"drop_count":3,"avg_m_rise":1.8,"v_m1":"Ja","v_low1":252.8,"v_high1":262.35,"v_m2":"Fb","v_low2":252.55,"v_high2":282.8,"v_m3":"Ma","v_low3":276.25,"v_high3":299.95,"v_m4":"Ap","v_low4":293.05,"v_high4":325.3,"v_m5":"My","v_low5":301,"v_high5":328,"v_m6":"Jn","v_low6":304.5,"v_high6":326,"v_m7":"Ju","v_low7":312.8,"v_high7":335.9,"v_m8":"Ag","v_low8":309.7,"v_high8":337.85,"v_m9":"Sp","v_low9":307.4,"v_high9":348.7,"v_m10":"Oc","v_low10":307.5,"v_high10":323.9,"v_m11":"Nv","v_low11":288.25,"v_high11":318.2,"v_m12":"Dc","v_low12":293.05,"v_high12":321.65,"a_buy":0,"a_sell":0,"b_buy":0,"b_sell":0,"c_buy":0,"c_sell":0 }
,{ "nse_code":"COLPAL","nse_name":"Colgate Palmolive (India) Limited","last_p":1083.3,"v52_hi":1178.35,"v52_lo":861.3,"v6_rate":1148.3,"v10_rate":1191.63,"v12_rate":1213.3,"v_time6":1,"v_time10":0,"v_time12":0,"close":1083.3,"last_pr":19.1,"rise_count":9,"drop_count":3,"avg_m_rise":1.55,"v_m1":"Ja","v_low1":861.3,"v_high1":924,"v_m2":"Fb","v_low2":878,"v_high2":928.8,"v_m3":"Ma","v_low3":888.6,"v_high3":1016.8,"v_m4":"Ap","v_low4":980,"v_high4":1047.8,"v_m5":"My","v_low5":966.75,"v_high5":1049,"v_m6":"Jn","v_low6":1009.15,"v_high6":1124,"v_m7":"Ju","v_low7":1055.1,"v_high7":1138.9,"v_m8":"Ag","v_low8":1027.5,"v_high8":1119,"v_m9":"Sp","v_low9":1050,"v_high9":1178.35,"v_m10":"Oc","v_low10":1026,"v_high10":1126,"v_m11":"Nv","v_low11":1015.1,"v_high11":1067,"v_m12":"Dc","v_low12":1022,"v_high12":1100.45,"a_buy":0,"a_sell":0,"b_buy":0,"b_sell":0,"c_buy":0,"c_sell":0 }
,{ "nse_code":"MOTHERSUMI","nse_name":"Motherson Sumi Systems Limited","last_p":385.9,"v52_hi":492.8,"v52_lo":302.05,"v6_rate":409.05,"v10_rate":424.49,"v12_rate":432.21,"v_time6":3,"v_time10":3,"v_time12":3,"close":385.9,"last_pr":13.38,"rise_count":10,"drop_count":2,"avg_m_rise":1.54,"v_m1":"Ja","v_low1":321,"v_high1":348.9,"v_m2":"Fb","v_low2":325.4,"v_high2":359.4,"v_m3":"Ma","v_low3":346,"v_high3":383,"v_m4":"Ap","v_low4":370.1,"v_high4":403.95,"v_m5":"My","v_low5":392.5,"v_high5":454.9,"v_m6":"Jn","v_low6":446.4,"v_high6":493,"v_m7":"Ju","v_low7":302.05,"v_high7":465.6,"v_m8":"Ag","v_low8":302.1,"v_high8":346.2,"v_m9":"Sp","v_low9":307.65,"v_high9":349.4,"v_m10":"Oc","v_low10":333.8,"v_high10":367.3,"v_m11":"Nv","v_low11":340.45,"v_high11":373.65,"v_m12":"Dc","v_low12":352.15,"v_high12":395.6,"a_buy":0,"a_sell":0,"b_buy":0,"b_sell":0,"c_buy":0,"c_sell":0 }
,{ "nse_code":"CADILAHC","nse_name":"Cadila Healthcare Limited","last_p":419.4,"v52_hi":560,"v52_lo":328.8,"v6_rate":444.56,"v10_rate":461.34,"v12_rate":469.73,"v_time6":10,"v_time10":8,"v_time12":7,"close":419.4,"last_pr":14.41,"rise_count":7,"drop_count":5,"avg_m_rise":1.5,"v_m1":"Ja","v_low1":329.4,"v_high1":380,"v_m2":"Fb","v_low2":348,"v_high2":460.75,"v_m3":"Ma","v_low3":407.9,"v_high3":456.5,"v_m4":"Ap","v_low4":438.45,"v_high4":466.85,"v_m5":"My","v_low5":417.05,"v_high5":497,"v_m6":"Jn","v_low6":464.15,"v_high6":559,"v_m7":"Ju","v_low7":508.1,"v_high7":560,"v_m8":"Ag","v_low8":435.1,"v_high8":553,"v_m9":"Sp","v_low9":451.2,"v_high9":519.45,"v_m10":"Oc","v_low10":471.25,"v_high10":511.9,"v_m11":"Nv","v_low11":427.55,"v_high11":515,"v_m12":"Dc","v_low12":401.45,"v_high12":434.75,"a_buy":0,"a_sell":0,"b_buy":0,"b_sell":0,"c_buy":0,"c_sell":0 }
,{ "nse_code":"AMBUJACEM","nse_name":"Ambuja Cements Limited","last_p":267.45,"v52_hi":291.5,"v52_lo":197,"v6_rate":283.5,"v10_rate":294.2,"v12_rate":299.54,"v_time6":3,"v_time10":0,"v_time12":0,"close":267.45,"last_pr":16.66,"rise_count":7,"drop_count":5,"avg_m_rise":1.42,"v_m1":"Ja","v_low1":210.55,"v_high1":233.5,"v_m2":"Fb","v_low2":226.25,"v_high2":244.9,"v_m3":"Ma","v_low3":222.9,"v_high3":238.35,"v_m4":"Ap","v_low4":235,"v_high4":252.75,"v_m5":"My","v_low5":233.05,"v_high5":270.85,"v_m6":"Jn","v_low6":228.7,"v_high6":249,"v_m7":"Ju","v_low7":230.75,"v_high7":275,"v_m8":"Ag","v_low8":258.1,"v_high8":282,"v_m9":"Sp","v_low9":260,"v_high9":291.5,"v_m10":"Oc","v_low10":266.05,"v_high10":288.8,"v_m11":"Nv","v_low11":259.25,"v_high11":287.5,"v_m12":"Dc","v_low12":255,"v_high12":272.4,"a_buy":0,"a_sell":0,"b_buy":0,"b_sell":0,"c_buy":0,"c_sell":0 }
,{ "nse_code":"ASIANPAINT","nse_name":"Asian Paints Limited","last_p":1135.5,"v52_hi":1262,"v52_lo":851.1,"v6_rate":1203.63,"v10_rate":1249.05,"v12_rate":1271.76,"v_time6":3,"v_time10":1,"v_time12":0,"close":1135.5,"last_pr":16.61,"rise_count":7,"drop_count":5,"avg_m_rise":1.36,"v_m1":"Ja","v_low1":926.9,"v_high1":989.6,"v_m2":"Fb","v_low2":953.85,"v_high2":1030,"v_m3":"Ma","v_low3":1006,"v_high3":1092.2,"v_m4":"Ap","v_low4":1033.7,"v_high4":1124.95,"v_m5":"My","v_low5":1080.5,"v_high5":1182,"v_m6":"Jn","v_low6":1083.3,"v_high6":1176,"v_m7":"Ju","v_low7":1075,"v_high7":1215.45,"v_m8":"Ag","v_low8":1114,"v_high8":1174,"v_m9":"Sp","v_low9":1123,"v_high9":1262,"v_m10":"Oc","v_low10":1135.5,"v_high10":1234,"v_m11":"Nv","v_low11":1132.5,"v_high11":1198.45,"v_m12":"Dc","v_low12":1099,"v_high12":1154,"a_buy":0,"a_sell":0,"b_buy":0,"b_sell":0,"c_buy":0,"c_sell":0 }
,{ "nse_code":"ULTRACEMCO","nse_name":"UltraTech Cement Limited","last_p":4333.1,"v52_hi":4533.1,"v52_lo":3050,"v6_rate":4593.09,"v10_rate":4766.41,"v12_rate":4853.07,"v_time6":0,"v_time10":0,"v_time12":0,"close":4333.1,"last_pr":16.1,"rise_count":8,"drop_count":4,"avg_m_rise":1.36,"v_m1":"Ja","v_low1":3300,"v_high1":3764,"v_m2":"Fb","v_low2":3634.1,"v_high2":3805,"v_m3":"Ma","v_low3":3720,"v_high3":4093.95,"v_m4":"Ap","v_low4":3926,"v_high4":4275,"v_m5":"My","v_low5":4045,"v_high5":4533.1,"v_m6":"Jn","v_low6":3840.55,"v_high6":4262,"v_m7":"Ju","v_low7":3935.45,"v_high7":4454.1,"v_m8":"Ag","v_low8":3842.3,"v_high8":4138.7,"v_m9":"Sp","v_low9":3773.3,"v_high9":4244,"v_m10":"Oc","v_low10":3854.2,"v_high10":4510,"v_m11":"Nv","v_low11":4128.05,"v_high11":4490.9,"v_m12":"Dc","v_low12":4016.35,"v_high12":4370,"a_buy":0,"a_sell":0,"b_buy":0,"b_sell":0,"c_buy":0,"c_sell":0 }
,{ "nse_code":"TATAPOWER","nse_name":"Tata Power Company Limited","last_p":90.85,"v52_hi":97.1,"v52_lo":72.55,"v6_rate":96.3,"v10_rate":99.94,"v12_rate":101.75,"v_time6":1,"v_time10":0,"v_time12":0,"close":90.85,"last_pr":15.53,"rise_count":7,"drop_count":5,"avg_m_rise":1.33,"v_m1":"Ja","v_low1":77.15,"v_high1":82.75,"v_m2":"Fb","v_low2":79,"v_high2":86,"v_m3":"Ma","v_low3":80.75,"v_high3":91.15,"v_m4":"Ap","v_low4":81.15,"v_high4":90.7,"v_m5":"My","v_low5":79.55,"v_high5":86,"v_m6":"Jn","v_low6":76.65,"v_high6":84,"v_m7":"Ju","v_low7":79.95,"v_high7":89.05,"v_m8":"Ag","v_low8":75.8,"v_high8":83.45,"v_m9":"Sp","v_low9":76.75,"v_high9":87.3,"v_m10":"Oc","v_low10":77.1,"v_high10":87.45,"v_m11":"Nv","v_low11":81.65,"v_high11":97.1,"v_m12":"Dc","v_low12":87,"v_high12":95.6,"a_buy":0,"a_sell":0,"b_buy":0,"b_sell":0,"c_buy":0,"c_sell":0 }
,{ "nse_code":"HEROMOTOCO","nse_name":"Hero MotoCorp Limited","last_p":3749.2,"v52_hi":4091.95,"v52_lo":2958,"v6_rate":3974.15,"v10_rate":4124.12,"v12_rate":4199.1,"v_time6":2,"v_time10":0,"v_time12":0,"close":3749.2,"last_pr":15.81,"rise_count":8,"drop_count":4,"avg_m_rise":1.32,"v_m1":"Ja","v_low1":3026.6,"v_high1":3275.95,"v_m2":"Fb","v_low2":3049.2,"v_high2":3319.2,"v_m3":"Ma","v_low3":3150,"v_high3":3412,"v_m4":"Ap","v_low4":3175,"v_high4":3364,"v_m5":"My","v_low5":3265,"v_high5":3762,"v_m6":"Jn","v_low6":3636.6,"v_high6":3881,"v_m7":"Ju","v_low7":3605,"v_high7":3804.05,"v_m8":"Ag","v_low8":3668.05,"v_high8":4044,"v_m9":"Sp","v_low9":3674.5,"v_high9":4091.95,"v_m10":"Oc","v_low10":3661.2,"v_high10":3870.05,"v_m11":"Nv","v_low11":3560.75,"v_high11":3882.9,"v_m12":"Dc","v_low12":3410,"v_high12":3793.9,"a_buy":0,"a_sell":0,"b_buy":0,"b_sell":0,"c_buy":0,"c_sell":0 }
,{ "nse_code":"ICICIBANK","nse_name":"ICICI Bank Limited","last_p":315.8,"v52_hi":332.35,"v52_lo":246.7,"v6_rate":334.75,"v10_rate":347.38,"v12_rate":353.7,"v_time6":0,"v_time10":0,"v_time12":0,"close":315.8,"last_pr":15.33,"rise_count":6,"drop_count":6,"avg_m_rise":1.31,"v_m1":"Ja","v_low1":255.15,"v_high1":275.6,"v_m2":"Fb","v_low2":262.8,"v_high2":292.7,"v_m3":"Ma","v_low3":264.5,"v_high3":288.2,"v_m4":"Ap","v_low4":265.2,"v_high4":291.6,"v_m5":"My","v_low5":271.25,"v_high5":327.4,"v_m6":"Jn","v_low6":283.45,"v_high6":327,"v_m7":"Ju","v_low7":286.15,"v_high7":314.45,"v_m8":"Ag","v_low8":261.55,"v_high8":305.2,"v_m9":"Sp","v_low9":269.15,"v_high9":300,"v_m10":"Oc","v_low10":255,"v_high10":314.65,"v_m11":"Nv","v_low11":302.4,"v_high11":332.35,"v_m12":"Dc","v_low12":287,"v_high12":317.85,"a_buy":0,"a_sell":0,"b_buy":0,"b_sell":0,"c_buy":0,"c_sell":0 }
,{ "nse_code":"SHREECEM","nse_name":"Shree Cements Limited","last_p":17805.45,"v52_hi":20538,"v52_lo":13140.3,"v6_rate":18873.78,"v10_rate":19586,"v12_rate":19942.1,"v_time6":6,"v_time10":3,"v_time12":1,"close":17805.45,"last_pr":14.3,"rise_count":8,"drop_count":4,"avg_m_rise":1.25,"v_m1":"Ja","v_low1":14650.05,"v_high1":16080,"v_m2":"Fb","v_low2":14930.25,"v_high2":16718.1,"v_m3":"Ma","v_low3":15654,"v_high3":17500,"v_m4":"Ap","v_low4":16901,"v_high4":19700.05,"v_m5":"My","v_low5":17010,"v_high5":20538,"v_m6":"Jn","v_low6":16501,"v_high6":18707,"v_m7":"Ju","v_low7":16827.65,"v_high7":19000,"v_m8":"Ag","v_low8":16759.05,"v_high8":18799.9,"v_m9":"Sp","v_low9":17049,"v_high9":19260,"v_m10":"Oc","v_low10":18127.1,"v_high10":19603.95,"v_m11":"Nv","v_low11":16752,"v_high11":19399,"v_m12":"Dc","v_low12":16750,"v_high12":18380,"a_buy":0,"a_sell":0,"b_buy":0,"b_sell":0,"c_buy":0,"c_sell":0 }
,{ "nse_code":"ZEEL","nse_name":"Zee Entertainment Enterprises Limited","last_p":580.55,"v52_hi":596.65,"v52_lo":427.65,"v6_rate":615.38,"v10_rate":638.61,"v12_rate":650.22,"v_time6":0,"v_time10":0,"v_time12":0,"close":580.55,"last_pr":14.99,"rise_count":7,"drop_count":5,"avg_m_rise":1.22,"v_m1":"Ja","v_low1":465.05,"v_high1":511,"v_m2":"Fb","v_low2":487.4,"v_high2":532.85,"v_m3":"Ma","v_low3":493.65,"v_high3":541,"v_m4":"Ap","v_low4":515.7,"v_high4":555,"v_m5":"My","v_low5":493.85,"v_high5":548.25,"v_m6":"Jn","v_low6":480,"v_high6":529,"v_m7":"Ju","v_low7":458.1,"v_high7":560,"v_m8":"Ag","v_low8":500.2,"v_high8":550.5,"v_m9":"Sp","v_low9":516.7,"v_high9":551.05,"v_m10":"Oc","v_low10":477,"v_high10":550.75,"v_m11":"Nv","v_low11":493.9,"v_high11":596.65,"v_m12":"Dc","v_low12":553.2,"v_high12":587.6,"a_buy":0,"a_sell":0,"b_buy":0,"b_sell":0,"c_buy":0,"c_sell":0 }
,{ "nse_code":"BAJAJ-AUTO","nse_name":"Bajaj Auto Limited","last_p":3301.2,"v52_hi":3373.8,"v52_lo":2551,"v6_rate":3499.27,"v10_rate":3631.32,"v12_rate":3697.34,"v_time6":0,"v_time10":0,"v_time12":0,"close":3301.2,"last_pr":14.42,"rise_count":7,"drop_count":5,"avg_m_rise":1.18,"v_m1":"Ja","v_low1":2681.5,"v_high1":2919,"v_m2":"Fb","v_low2":2751,"v_high2":2872,"v_m3":"Ma","v_low3":2752.05,"v_high3":2948.7,"v_m4":"Ap","v_low4":2754.75,"v_high4":2915,"v_m5":"My","v_low5":2750,"v_high5":3047.5,"v_m6":"Jn","v_low6":2761,"v_high6":2930,"v_m7":"Ju","v_low7":2694.5,"v_high7":2869.1,"v_m8":"Ag","v_low8":2704,"v_high8":2981,"v_m9":"Sp","v_low9":2827.9,"v_high9":3155.05,"v_m10":"Oc","v_low10":3105.65,"v_high10":3344.9,"v_m11":"Nv","v_low11":3146.05,"v_high11":3373.8,"v_m12":"Dc","v_low12":3038.9,"v_high12":3340,"a_buy":0,"a_sell":0,"b_buy":0,"b_sell":0,"c_buy":0,"c_sell":0 }
,{ "nse_code":"AXISBANK","nse_name":"Axis Bank Limited","last_p":554.5,"v52_hi":565.9,"v52_lo":424.4,"v6_rate":587.77,"v10_rate":609.95,"v12_rate":621.04,"v_time6":0,"v_time10":0,"v_time12":0,"close":554.5,"last_pr":13.44,"rise_count":7,"drop_count":5,"avg_m_rise":1.11,"v_m1":"Ja","v_low1":441.1,"v_high1":491.7,"v_m2":"Fb","v_low2":460,"v_high2":530,"v_m3":"Ma","v_low3":483,"v_high3":525.65,"v_m4":"Ap","v_low4":481,"v_high4":525,"v_m5":"My","v_low5":490.25,"v_high5":534.6,"v_m6":"Jn","v_low6":484.45,"v_high6":525,"v_m7":"Ju","v_low7":488.4,"v_high7":547.5,"v_m8":"Ag","v_low8":480,"v_high8":524.05,"v_m9":"Sp","v_low9":488.3,"v_high9":526,"v_m10":"Oc","v_low10":447.5,"v_high10":534.65,"v_m11":"Nv","v_low11":523,"v_high11":565.9,"v_m12":"Dc","v_low12":529.1,"v_high12":557.8,"a_buy":0,"a_sell":0,"b_buy":0,"b_sell":0,"c_buy":0,"c_sell":0 }
,{ "nse_code":"TCS","nse_name":"Tata Consultancy Services Limited","last_p":2588.95,"v52_hi":2777.4,"v52_lo":2153,"v6_rate":2744.29,"v10_rate":2847.85,"v12_rate":2899.62,"v_time6":1,"v_time10":0,"v_time12":0,"close":2588.95,"last_pr":12.36,"rise_count":7,"drop_count":5,"avg_m_rise":1.07,"v_m1":"Ja","v_low1":2200.05,"v_high1":2378.75,"v_m2":"Fb","v_low2":2153,"v_high2":2555,"v_m3":"Ma","v_low3":2406,"v_high3":2587.15,"v_m4":"Ap","v_low4":2252.8,"v_high4":2449,"v_m5":"My","v_low5":2268.5,"v_high5":2637.55,"v_m6":"Jn","v_low6":2323.1,"v_high6":2709,"v_m7":"Ju","v_low7":2325.5,"v_high7":2584.8,"v_m8":"Ag","v_low8":2460.1,"v_high8":2549.9,"v_m9":"Sp","v_low9":2421.5,"v_high9":2541,"v_m10":"Oc","v_low10":2424.4,"v_high10":2640,"v_m11":"Nv","v_low11":2578.85,"v_high11":2777.4,"v_m12":"Dc","v_low12":2494.35,"v_high12":2672.65,"a_buy":0,"a_sell":0,"b_buy":0,"b_sell":0,"c_buy":0,"c_sell":0 }
,{ "nse_code":"ICICIPRULI","nse_name":"ICICI Prudential Life Insurance Company Limited","last_p":394.85,"v52_hi":509.4,"v52_lo":294.1,"v6_rate":418.54,"v10_rate":434.34,"v12_rate":442.23,"v_time6":6,"v_time10":4,"v_time12":4,"close":394.85,"last_pr":10.26,"rise_count":6,"drop_count":6,"avg_m_rise":1.03,"v_m1":"Ja","v_low1":330,"v_high1":363.5,"v_m2":"Fb","v_low2":342.5,"v_high2":368.75,"v_m3":"Ma","v_low3":358.95,"v_high3":386.95,"v_m4":"Ap","v_low4":381,"v_high4":424,"v_m5":"My","v_low5":387,"v_high5":420.75,"v_m6":"Jn","v_low6":397.7,"v_high6":485,"v_m7":"Ju","v_low7":433.15,"v_high7":509.4,"v_m8":"Ag","v_low8":401.9,"v_high8":459.3,"v_m9":"Sp","v_low9":378.5,"v_high9":451.25,"v_m10":"Oc","v_low10":385.35,"v_high10":416.85,"v_m11":"Nv","v_low11":370.1,"v_high11":409.65,"v_m12":"Dc","v_low12":363.2,"v_high12":400.8,"a_buy":0,"a_sell":0,"b_buy":0,"b_sell":0,"c_buy":0,"c_sell":0 }
,{ "nse_code":"CONCOR","nse_name":"Container Corporation of India Limited","last_p":1349.8,"v52_hi":1418,"v52_lo":984.4,"v6_rate":1430.79,"v10_rate":1484.78,"v12_rate":1511.78,"v_time6":0,"v_time10":0,"v_time12":0,"close":1349.8,"last_pr":11.49,"rise_count":7,"drop_count":5,"avg_m_rise":1.02,"v_m1":"Ja","v_low1":1136,"v_high1":1220,"v_m2":"Fb","v_low2":1163.8,"v_high2":1336,"v_m3":"Ma","v_low3":1202.05,"v_high3":1288.1,"v_m4":"Ap","v_low4":984.4,"v_high4":1288.25,"v_m5":"My","v_low5":1145.8,"v_high5":1251.6,"v_m6":"Jn","v_low6":1120,"v_high6":1213,"v_m7":"Ju","v_low7":1135.85,"v_high7":1213.95,"v_m8":"Ag","v_low8":1096.1,"v_high8":1344,"v_m9":"Sp","v_low9":1250.85,"v_high9":1413,"v_m10":"Oc","v_low10":1297.35,"v_high10":1399.2,"v_m11":"Nv","v_low11":1301,"v_high11":1418,"v_m12":"Dc","v_low12":1261.1,"v_high12":1360.2,"a_buy":0,"a_sell":0,"b_buy":0,"b_sell":0,"c_buy":0,"c_sell":0 }
 ]}
